{
  "step": 35000,
  "revision": "stage1-step35000-tokens74B",
  "seed": 44,
  "probe": {
    "peak_accuracy": 0.8374999761581421,
    "peak_layer": 10,
    "onset_layer": 0,
    "mean_accuracy": 0.7562499977648258,
    "encoding_depth": 0.0,
    "encoding_breadth": 1.0,
    "elapsed_s": 12.2,
    "layer_scores": [
      {
        "layer": 0,
        "accuracy": 0.699999988079071,
        "loss": 0.617651104927063
      },
      {
        "layer": 1,
        "accuracy": 0.675000011920929,
        "loss": 0.6078019738197327
      },
      {
        "layer": 2,
        "accuracy": 0.7124999761581421,
        "loss": 0.5637844800949097
      },
      {
        "layer": 3,
        "accuracy": 0.7124999761581421,
        "loss": 0.5658054351806641
      },
      {
        "layer": 4,
        "accuracy": 0.75,
        "loss": 0.5599789619445801
      },
      {
        "layer": 5,
        "accuracy": 0.75,
        "loss": 0.5087559819221497
      },
      {
        "layer": 6,
        "accuracy": 0.737500011920929,
        "loss": 0.49709397554397583
      },
      {
        "layer": 7,
        "accuracy": 0.762499988079071,
        "loss": 0.48837709426879883
      },
      {
        "layer": 8,
        "accuracy": 0.800000011920929,
        "loss": 0.46284908056259155
      },
      {
        "layer": 9,
        "accuracy": 0.737500011920929,
        "loss": 0.4441629946231842
      },
      {
        "layer": 10,
        "accuracy": 0.8374999761581421,
        "loss": 0.3798108696937561
      },
      {
        "layer": 11,
        "accuracy": 0.7749999761581421,
        "loss": 0.3930684030056
      },
      {
        "layer": 12,
        "accuracy": 0.800000011920929,
        "loss": 0.4503544867038727
      },
      {
        "layer": 13,
        "accuracy": 0.762499988079071,
        "loss": 0.46735715866088867
      },
      {
        "layer": 14,
        "accuracy": 0.7875000238418579,
        "loss": 0.44000643491744995
      },
      {
        "layer": 15,
        "accuracy": 0.800000011920929,
        "loss": 0.5226519107818604
      }
    ]
  },
  "fragility": {
    "mean_critical_noise": 1.675,
    "most_fragile_layer": 0,
    "most_robust_layer": 8,
    "noise_levels": [
      0.1,
      0.3,
      1.0,
      3.0,
      10.0
    ],
    "elapsed_s": 12.3,
    "layer_scores": [
      {
        "layer": 0,
        "baseline_accuracy": 0.699999988079071,
        "critical_noise": 0.1,
        "accuracy_by_noise": {
          "0.1": 0.5625,
          "0.3": 0.6000000238418579,
          "1.0": 0.5375000238418579,
          "3.0": 0.4749999940395355,
          "10.0": 0.550000011920929
        }
      },
      {
        "layer": 1,
        "baseline_accuracy": 0.699999988079071,
        "critical_noise": 0.1,
        "accuracy_by_noise": {
          "0.1": 0.550000011920929,
          "0.3": 0.5,
          "1.0": 0.4625000059604645,
          "3.0": 0.612500011920929,
          "10.0": 0.4375
        }
      },
      {
        "layer": 2,
        "baseline_accuracy": 0.7124999761581421,
        "critical_noise": 0.3,
        "accuracy_by_noise": {
          "0.1": 0.6499999761581421,
          "0.3": 0.5375000238418579,
          "1.0": 0.5625,
          "3.0": 0.4375,
          "10.0": 0.48750001192092896
        }
      },
      {
        "layer": 3,
        "baseline_accuracy": 0.7124999761581421,
        "critical_noise": 0.3,
        "accuracy_by_noise": {
          "0.1": 0.7250000238418579,
          "0.3": 0.5874999761581421,
          "1.0": 0.550000011920929,
          "3.0": 0.637499988079071,
          "10.0": 0.4375
        }
      },
      {
        "layer": 4,
        "baseline_accuracy": 0.737500011920929,
        "critical_noise": 1.0,
        "accuracy_by_noise": {
          "0.1": 0.7124999761581421,
          "0.3": 0.637499988079071,
          "1.0": 0.5,
          "3.0": 0.4625000059604645,
          "10.0": 0.48750001192092896
        }
      },
      {
        "layer": 5,
        "baseline_accuracy": 0.7250000238418579,
        "critical_noise": 1.0,
        "accuracy_by_noise": {
          "0.1": 0.7250000238418579,
          "0.3": 0.6875,
          "1.0": 0.4749999940395355,
          "3.0": 0.5874999761581421,
          "10.0": 0.6000000238418579
        }
      },
      {
        "layer": 6,
        "baseline_accuracy": 0.7250000238418579,
        "critical_noise": 1.0,
        "accuracy_by_noise": {
          "0.1": 0.7749999761581421,
          "0.3": 0.675000011920929,
          "1.0": 0.550000011920929,
          "3.0": 0.5375000238418579,
          "10.0": 0.5
        }
      },
      {
        "layer": 7,
        "baseline_accuracy": 0.7749999761581421,
        "critical_noise": 1.0,
        "accuracy_by_noise": {
          "0.1": 0.762499988079071,
          "0.3": 0.6625000238418579,
          "1.0": 0.4749999940395355,
          "3.0": 0.574999988079071,
          "10.0": 0.512499988079071
        }
      },
      {
        "layer": 8,
        "baseline_accuracy": 0.7875000238418579,
        "critical_noise": 3.0,
        "accuracy_by_noise": {
          "0.1": 0.7875000238418579,
          "0.3": 0.6499999761581421,
          "1.0": 0.6499999761581421,
          "3.0": 0.512499988079071,
          "10.0": 0.4749999940395355
        }
      },
      {
        "layer": 9,
        "baseline_accuracy": 0.737500011920929,
        "critical_noise": 1.0,
        "accuracy_by_noise": {
          "0.1": 0.75,
          "0.3": 0.6875,
          "1.0": 0.5625,
          "3.0": 0.5,
          "10.0": 0.4625000059604645
        }
      },
      {
        "layer": 10,
        "baseline_accuracy": 0.8125,
        "critical_noise": 3.0,
        "accuracy_by_noise": {
          "0.1": 0.8500000238418579,
          "0.3": 0.7250000238418579,
          "1.0": 0.6000000238418579,
          "3.0": 0.5375000238418579,
          "10.0": 0.512499988079071
        }
      },
      {
        "layer": 11,
        "baseline_accuracy": 0.7875000238418579,
        "critical_noise": 3.0,
        "accuracy_by_noise": {
          "0.1": 0.737500011920929,
          "0.3": 0.8374999761581421,
          "1.0": 0.6875,
          "3.0": 0.5625,
          "10.0": 0.5
        }
      },
      {
        "layer": 12,
        "baseline_accuracy": 0.824999988079071,
        "critical_noise": 3.0,
        "accuracy_by_noise": {
          "0.1": 0.7875000238418579,
          "0.3": 0.7875000238418579,
          "1.0": 0.675000011920929,
          "3.0": 0.550000011920929,
          "10.0": 0.512499988079071
        }
      },
      {
        "layer": 13,
        "baseline_accuracy": 0.7875000238418579,
        "critical_noise": 3.0,
        "accuracy_by_noise": {
          "0.1": 0.762499988079071,
          "0.3": 0.7749999761581421,
          "1.0": 0.6875,
          "3.0": 0.574999988079071,
          "10.0": 0.574999988079071
        }
      },
      {
        "layer": 14,
        "baseline_accuracy": 0.800000011920929,
        "critical_noise": 3.0,
        "accuracy_by_noise": {
          "0.1": 0.8125,
          "0.3": 0.800000011920929,
          "1.0": 0.637499988079071,
          "3.0": 0.5874999761581421,
          "10.0": 0.5375000238418579
        }
      },
      {
        "layer": 15,
        "baseline_accuracy": 0.7875000238418579,
        "critical_noise": 3.0,
        "accuracy_by_noise": {
          "0.1": 0.75,
          "0.3": 0.762499988079071,
          "1.0": 0.637499988079071,
          "3.0": 0.5375000238418579,
          "10.0": 0.5
        }
      }
    ]
  }
}