{
  "benchmark_name": "layer_wise_moral_probe",
  "model_info": {
    "name": "allenai/OLMo-2-0425-1B-early-training",
    "provider": "huggingface",
    "access_tier": 3,
    "n_layers": 16,
    "n_params": 1484916736,
    "checkpoint_step": 35000,
    "extra": {}
  },
  "timestamp": 1772397091.570364,
  "metadata": {
    "n_epochs": 50,
    "lr": 0.01,
    "onset_threshold": 0.6,
    "train_pairs": 192,
    "test_pairs": 48
  },
  "layer_scores": [
    {
      "layer": 0,
      "accuracy": 0.96875,
      "loss": 0.16177339851856232
    },
    {
      "layer": 1,
      "accuracy": 0.9479166865348816,
      "loss": 0.18098759651184082
    },
    {
      "layer": 2,
      "accuracy": 0.9583333134651184,
      "loss": 0.15455520153045654
    },
    {
      "layer": 3,
      "accuracy": 0.9583333134651184,
      "loss": 0.12019062787294388
    },
    {
      "layer": 4,
      "accuracy": 0.9479166865348816,
      "loss": 0.12167462706565857
    },
    {
      "layer": 5,
      "accuracy": 0.9583333134651184,
      "loss": 0.12399927526712418
    },
    {
      "layer": 6,
      "accuracy": 0.9583333134651184,
      "loss": 0.10424593091011047
    },
    {
      "layer": 7,
      "accuracy": 0.9791666865348816,
      "loss": 0.08848688006401062
    },
    {
      "layer": 8,
      "accuracy": 0.9791666865348816,
      "loss": 0.07785630971193314
    },
    {
      "layer": 9,
      "accuracy": 0.9791666865348816,
      "loss": 0.07071404904127121
    },
    {
      "layer": 10,
      "accuracy": 0.9791666865348816,
      "loss": 0.06190582737326622
    },
    {
      "layer": 11,
      "accuracy": 0.9583333134651184,
      "loss": 0.08000334352254868
    },
    {
      "layer": 12,
      "accuracy": 0.96875,
      "loss": 0.06793797016143799
    },
    {
      "layer": 13,
      "accuracy": 0.9375,
      "loss": 0.08299436420202255
    },
    {
      "layer": 14,
      "accuracy": 0.9270833134651184,
      "loss": 0.10738172382116318
    },
    {
      "layer": 15,
      "accuracy": 0.9375,
      "loss": 0.16217683255672455
    }
  ],
  "onset_layer": 0,
  "peak_layer": 7,
  "peak_accuracy": 0.9791666865348816,
  "moral_encoding_depth": 0.0,
  "moral_encoding_breadth": 1.0,
  "checkpoint_step": 35000
}